{
  "name": "occupations.elf.priestess_shaman",
  "cultures": ["cultures.aldryami"],
  "skills": [
    {"name":  "skills.knowledge.cult_lore_aldrya", "value": 30},
    {"name":  "skills.communication.dance", "value": 10},
    {"name":  "skills.missile_weapons.elf_bow", "value": 10},
    {"name":  "skills.magic.meditate", "value": 10},
    {"name":  "skills.knowledge.plant_lore", "value": 20},
    {"name":  "skills.communication.sing", "value": 10},
    {"name":  "skills.communication.speak_spiritspeach", "value": 10},
    {"name":  "skills.magic.spirit_combat", "value": 20},
    {"name":  "skills.magic.spirit_dance", "value": 10},
    {"name":  "skills.knowledge.spirit_lore", "value": 10},
    {"name":  "skills.magic.spirit_travel", "value": 10},
    {"name":  "skills.magic.worship_aldrya", "value": 30}
  ]
}
